Workbook

Sheet Instructions
A1: Agency Profitability Worksheet
A3: Use this workbook to forecast margin before accepting work and to compare the approved plan with actual delivery.
A5: Workflow
A6: 1 | B6: Add one row per project on Project P&L.
A7: 2 | B7: Enter revenue, planned hours, hourly internal cost, and other direct costs.
A8: 3 | B8: Update actual hours and costs weekly; formulas calculate variance and margin.
A9: 4 | B9: Use Capacity Plan before accepting new work.
A10: 5 | B10: Use Change Impact to price extra work before production begins.
A13: Definitions
A14: Gross margin % | B14: (Revenue − direct cost) ÷ Revenue.
A15: Forecast margin % | B15: (Revenue − forecast direct cost) ÷ Revenue.
A16: Hours variance | B16: Actual hours − planned hours. Positive means over plan.
A17: Change request | B17: Any added deliverable, revision, channel, meeting, or deadline change outside the approved baseline.

Sheet Project P&L
A1: Project ID | B1: Client | C1: Service | D1: Status | E1: Revenue | F1: Planned hours | G1: Actual hours | H1: Internal hourly cost | I1: Other direct cost | J1: Forecast cost | K1: Actual cost | L1: Forecast margin % | M1: Actual margin % | N1: Hours variance | O1: Margin flag | P1: Next action
J2: =IF(E2="","",F2*H2+I2) | K2: =IF(E2="","",G2*H2+I2) | L2: =IFERROR((E2-J2)/E2,"") | M2: =IFERROR((E2-K2)/E2,"") | N2: =IF(E2="","",G2-F2) | O2: =IF(E2="","",IF(M2<0.45,"RED",IF(M2<0.6,"AMBER","GREEN")))
J3: =IF(E3="","",F3*H3+I3) | K3: =IF(E3="","",G3*H3+I3) | L3: =IFERROR((E3-J3)/E3,"") | M3: =IFERROR((E3-K3)/E3,"") | N3: =IF(E3="","",G3-F3) | O3: =IF(E3="","",IF(M3<0.45,"RED",IF(M3<0.6,"AMBER","GREEN")))
J4: =IF(E4="","",F4*H4+I4) | K4: =IF(E4="","",G4*H4+I4) | L4: =IFERROR((E4-J4)/E4,"") | M4: =IFERROR((E4-K4)/E4,"") | N4: =IF(E4="","",G4-F4) | O4: =IF(E4="","",IF(M4<0.45,"RED",IF(M4<0.6,"AMBER","GREEN")))
J5: =IF(E5="","",F5*H5+I5) | K5: =IF(E5="","",G5*H5+I5) | L5: =IFERROR((E5-J5)/E5,"") | M5: =IFERROR((E5-K5)/E5,"") | N5: =IF(E5="","",G5-F5) | O5: =IF(E5="","",IF(M5<0.45,"RED",IF(M5<0.6,"AMBER","GREEN")))
J6: =IF(E6="","",F6*H6+I6) | K6: =IF(E6="","",G6*H6+I6) | L6: =IFERROR((E6-J6)/E6,"") | M6: =IFERROR((E6-K6)/E6,"") | N6: =IF(E6="","",G6-F6) | O6: =IF(E6="","",IF(M6<0.45,"RED",IF(M6<0.6,"AMBER","GREEN")))
J7: =IF(E7="","",F7*H7+I7) | K7: =IF(E7="","",G7*H7+I7) | L7: =IFERROR((E7-J7)/E7,"") | M7: =IFERROR((E7-K7)/E7,"") | N7: =IF(E7="","",G7-F7) | O7: =IF(E7="","",IF(M7<0.45,"RED",IF(M7<0.6,"AMBER","GREEN")))
J8: =IF(E8="","",F8*H8+I8) | K8: =IF(E8="","",G8*H8+I8) | L8: =IFERROR((E8-J8)/E8,"") | M8: =IFERROR((E8-K8)/E8,"") | N8: =IF(E8="","",G8-F8) | O8: =IF(E8="","",IF(M8<0.45,"RED",IF(M8<0.6,"AMBER","GREEN")))
J9: =IF(E9="","",F9*H9+I9) | K9: =IF(E9="","",G9*H9+I9) | L9: =IFERROR((E9-J9)/E9,"") | M9: =IFERROR((E9-K9)/E9,"") | N9: =IF(E9="","",G9-F9) | O9: =IF(E9="","",IF(M9<0.45,"RED",IF(M9<0.6,"AMBER","GREEN")))
J10: =IF(E10="","",F10*H10+I10) | K10: =IF(E10="","",G10*H10+I10) | L10: =IFERROR((E10-J10)/E10,"") | M10: =IFERROR((E10-K10)/E10,"") | N10: =IF(E10="","",G10-F10) | O10: =IF(E10="","",IF(M10<0.45,"RED",IF(M10<0.6,"AMBER","GREEN")))
J11: =IF(E11="","",F11*H11+I11) | K11: =IF(E11="","",G11*H11+I11) | L11: =IFERROR((E11-J11)/E11,"") | M11: =IFERROR((E11-K11)/E11,"") | N11: =IF(E11="","",G11-F11) | O11: =IF(E11="","",IF(M11<0.45,"RED",IF(M11<0.6,"AMBER","GREEN")))
J12: =IF(E12="","",F12*H12+I12) | K12: =IF(E12="","",G12*H12+I12) | L12: =IFERROR((E12-J12)/E12,"") | M12: =IFERROR((E12-K12)/E12,"") | N12: =IF(E12="","",G12-F12) | O12: =IF(E12="","",IF(M12<0.45,"RED",IF(M12<0.6,"AMBER","GREEN")))
J13: =IF(E13="","",F13*H13+I13) | K13: =IF(E13="","",G13*H13+I13) | L13: =IFERROR((E13-J13)/E13,"") | M13: =IFERROR((E13-K13)/E13,"") | N13: =IF(E13="","",G13-F13) | O13: =IF(E13="","",IF(M13<0.45,"RED",IF(M13<0.6,"AMBER","GREEN")))
... J101: =IF(E101="","",F101*H101+I101) | K101: =IF(E101="","",G101*H101+I101) | L101: =IFERROR((E101-J101)/E101,"") | M101: =IFERROR((E101-K101)/E101,"") | N101: =IF(E101="","",G101-F101) | O101: =IF(E101="","",IF(M101<0.45,"RED",IF(M101<0.6,"AMBER","GREEN")))

Sheet Capacity Plan
A1: Team member | B1: Role | C1: Weekly capacity hours | D1: Utilization target % | E1: Committed hours | F1: Reserved ops hours | G1: Available delivery hours | H1: Overallocated?
G2: =IF(A2="","",C2*D2-E2-F2) | H2: =IF(A2="","",IF(G2<0,"YES","NO"))
G3: =IF(A3="","",C3*D3-E3-F3) | H3: =IF(A3="","",IF(G3<0,"YES","NO"))
G4: =IF(A4="","",C4*D4-E4-F4) | H4: =IF(A4="","",IF(G4<0,"YES","NO"))
G5: =IF(A5="","",C5*D5-E5-F5) | H5: =IF(A5="","",IF(G5<0,"YES","NO"))
G6: =IF(A6="","",C6*D6-E6-F6) | H6: =IF(A6="","",IF(G6<0,"YES","NO"))
G7: =IF(A7="","",C7*D7-E7-F7) | H7: =IF(A7="","",IF(G7<0,"YES","NO"))
G8: =IF(A8="","",C8*D8-E8-F8) | H8: =IF(A8="","",IF(G8<0,"YES","NO"))
G9: =IF(A9="","",C9*D9-E9-F9) | H9: =IF(A9="","",IF(G9<0,"YES","NO"))
G10: =IF(A10="","",C10*D10-E10-F10) | H10: =IF(A10="","",IF(G10<0,"YES","NO"))
G11: =IF(A11="","",C11*D11-E11-F11) | H11: =IF(A11="","",IF(G11<0,"YES","NO"))
G12: =IF(A12="","",C12*D12-E12-F12) | H12: =IF(A12="","",IF(G12<0,"YES","NO"))
G13: =IF(A13="","",C13*D13-E13-F13) | H13: =IF(A13="","",IF(G13<0,"YES","NO"))
... G21: =IF(A21="","",C21*D21-E21-F21) | H21: =IF(A21="","",IF(G21<0,"YES","NO"))

Sheet Change Impact
A1: Change ID | B1: Project ID | C1: Requested item | D1: Extra hours | E1: Hourly sell rate | F1: Added price | G1: Internal cost | H1: Net contribution | I1: Approval status | J1: Decision date
F2: =IF(D2="","",D2*E2) | G2: =IF(D2="","",D2*0) | H2: =IF(F2="","",F2-G2)
F3: =IF(D3="","",D3*E3) | G3: =IF(D3="","",D3*0) | H3: =IF(F3="","",F3-G3)
F4: =IF(D4="","",D4*E4) | G4: =IF(D4="","",D4*0) | H4: =IF(F4="","",F4-G4)
F5: =IF(D5="","",D5*E5) | G5: =IF(D5="","",D5*0) | H5: =IF(F5="","",F5-G5)
F6: =IF(D6="","",D6*E6) | G6: =IF(D6="","",D6*0) | H6: =IF(F6="","",F6-G6)
F7: =IF(D7="","",D7*E7) | G7: =IF(D7="","",D7*0) | H7: =IF(F7="","",F7-G7)
F8: =IF(D8="","",D8*E8) | G8: =IF(D8="","",D8*0) | H8: =IF(F8="","",F8-G8)
F9: =IF(D9="","",D9*E9) | G9: =IF(D9="","",D9*0) | H9: =IF(F9="","",F9-G9)
F10: =IF(D10="","",D10*E10) | G10: =IF(D10="","",D10*0) | H10: =IF(F10="","",F10-G10)
F11: =IF(D11="","",D11*E11) | G11: =IF(D11="","",D11*0) | H11: =IF(F11="","",F11-G11)
F12: =IF(D12="","",D12*E12) | G12: =IF(D12="","",D12*0) | H12: =IF(F12="","",F12-G12)
F13: =IF(D13="","",D13*E13) | G13: =IF(D13="","",D13*0) | H13: =IF(F13="","",F13-G13)
... F51: =IF(D51="","",D51*E51) | G51: =IF(D51="","",D51*0) | H51: =IF(F51="","",F51-G51)

Sheet Dashboard
A1: Agency Profitability Dashboard
A3: Total revenue | B3: =SUM('Project P&L'!E2:E101) | D3: Project | E3: Actual margin %
A4: Forecast direct cost | B4: =SUM('Project P&L'!J2:J101) | D4: =IF('Project P&L'!A2="","",'Project P&L'!A2) | E4: =IF('Project P&L'!A2="","",'Project P&L'!M2)
A5: Actual direct cost | B5: =SUM('Project P&L'!K2:K101) | D5: =IF('Project P&L'!A3="","",'Project P&L'!A3) | E5: =IF('Project P&L'!A3="","",'Project P&L'!M3)
A6: Forecast margin % | B6: =IFERROR((B3-B4)/B3,"") | D6: =IF('Project P&L'!A4="","",'Project P&L'!A4) | E6: =IF('Project P&L'!A4="","",'Project P&L'!M4)
A7: Actual margin % | B7: =IFERROR((B3-B5)/B3,"") | D7: =IF('Project P&L'!A5="","",'Project P&L'!A5) | E7: =IF('Project P&L'!A5="","",'Project P&L'!M5)
A8: Planned hours | B8: =SUM('Project P&L'!F2:F101) | D8: =IF('Project P&L'!A6="","",'Project P&L'!A6) | E8: =IF('Project P&L'!A6="","",'Project P&L'!M6)
A9: Actual hours | B9: =SUM('Project P&L'!G2:G101) | D9: =IF('Project P&L'!A7="","",'Project P&L'!A7) | E9: =IF('Project P&L'!A7="","",'Project P&L'!M7)
A10: Open change value | B10: =SUMIF('Change Impact'!I2:I51,"<>Approved",'Change Impact'!F2:F51) | D10: =IF('Project P&L'!A8="","",'Project P&L'!A8) | E10: =IF('Project P&L'!A8="","",'Project P&L'!M8)
D11: =IF('Project P&L'!A9="","",'Project P&L'!A9) | E11: =IF('Project P&L'!A9="","",'Project P&L'!M9)
D12: =IF('Project P&L'!A10="","",'Project P&L'!A10) | E12: =IF('Project P&L'!A10="","",'Project P&L'!M10)
D13: =IF('Project P&L'!A11="","",'Project P&L'!A11) | E13: =IF('Project P&L'!A11="","",'Project P&L'!M11)
